{"id": "Jinx", "key": "222", "name": "暴走萝莉", "title": "金克丝", "image": "//game.gtimg.cn/images/lol/act/img/champion/Jinx.png", "skins": [{"id": "222000", "num": 0, "name": "默认皮肤", "chromas": false, "image": "//game.gtimg.cn/images/lol/act/img/skinloading/222000.jpg", "hash": "https://cdn.jsdelivr.net/gh/Virace/lol-audio-events-hashtable@main/VO/zh_CN/characters/jinx/skin0.json", "description": null}, {"id": "222001", "num": 1, "name": "黑帮狂花 金克丝", "chromas": false, "image": "//game.gtimg.cn/images/lol/act/img/skinloading/222001.jpg", "hash": "https://cdn.jsdelivr.net/gh/Virace/lol-audio-events-hashtable@main/VO/zh_CN/characters/jinx/skin1.json", "description": "警察们称她为“美丽公主”，金克丝作为一个精神错乱的女杀手和格雷福斯家族的关系并不紧密。她经常被像一枚定时炸弹那样被送到商业上的竞争对手那里，只要轻微的挑衅就能惹毛她，她开始疯狂屠杀，尸体堆得跟天花板一样高。 "}, {"id": "222004", "num": 4, "name": "星之守护者 金克丝", "chromas": false, "image": "//game.gtimg.cn/images/lol/act/img/skinloading/222004.jpg", "hash": "https://cdn.jsdelivr.net/gh/Virace/lol-audio-events-hashtable@main/VO/zh_CN/characters/jinx/skin4.json", "description": "金克丝让自己的队友很头疼，她是个行事冲动、玩世不恭的星之守护者，只喜欢巨大闪亮的爆炸。不过只要战斗开始，金克丝必定会冲锋陷阵，保护其他人，尤其是她的儿时密友拉克丝。"}, {"id": "222020", "num": 20, "name": "源计划：疯狂 金克丝", "chromas": true, "image": "//game.gtimg.cn/images/lol/act/img/skinloading/222020.jpg", "hash": "https://cdn.jsdelivr.net/gh/Virace/lol-audio-events-hashtable@main/VO/zh_CN/characters/jinx/skin20.json", "description": "金克丝曾志愿接受源计划的转化，但从来没有预想过一次致命的能量故障会扰乱掉她的记忆核心，仅留给她一个受她脑中的躁狂声音所驱动的人格。看似痴迷于毁灭本身的她开始显示出一些远比单纯的记忆破碎更加罪恶之物的迹象：冷酷、审慎的源计划影响力。"}], "blurb": "神经狂躁、冲动任性、劣迹斑斑……金克丝出身自祖安，生来就爱不计后果地大搞破坏。她就是一座人形自走军火库，所经之处必定会留下夺目的火光和震耳的爆炸。金克丝最讨厌无聊，所以不管她去到哪里，混乱和骚动就会如期而至，这就是她留下的“到此一游”。", "allytips": ["- 火箭并不总是最佳选择！金克丝的轻机枪在预热完毕后，也拥有难以置信的威力。当敌方英雄快要抓到你时，就换成轻机枪射个痛快吧！ ", "- 金克丝的火箭会对爆炸范围内的所有敌人造成完全伤害。在对线时，可以朝小兵发射火箭来溅射附近的敌方英雄，并且还不会吸引小兵的仇恨。", "- 当战斗开始时，尽量呆在交战区域的边缘位置，用火箭和震荡电磁波来从远处轰击对手。除非你觉得己方优势很明显，否则不要跑上前去用轻机枪扫射。"], "enemytips": ["- 金克丝的轻机枪需要花费时间来预热，才能发挥全部实力。如果你看到她在远处发射火箭，就要尽量突进过去将她放倒。", "- 你离金克丝越近，她的终极技能对你造成的伤害值就越低。", "- 金克丝的陷阱手雷的冷却时间很长，并且是她的主要防身武器。如果手雷没扔中敌人，就会在交战时陷入困境。  "], "version": "11.11"}