{"id": "Seraphine", "key": "147", "name": "星籁歌姬", "title": "萨勒芬妮", "image": "//game.gtimg.cn/images/lol/act/img/champion/Seraphine.png", "skins": [{"id": "147000", "num": 0, "name": "默认皮肤", "chromas": false, "image": "//game.gtimg.cn/images/lol/act/img/skinloading/147000.jpg", "hash": "https://cdn.jsdelivr.net/gh/Virace/lol-audio-events-hashtable@main/VO/zh_CN/characters/seraphine/skin0.json", "description": null}, {"id": "147001", "num": 1, "name": "K/DA ALL OUT 萨勒芬妮 独立音乐人", "chromas": false, "image": "//game.gtimg.cn/images/lol/act/img/skinloading/147001.jpg", "hash": "https://cdn.jsdelivr.net/gh/Virace/lol-audio-events-hashtable@main/VO/zh_CN/characters/seraphine/skin1.json", "description": "萨勒芬妮有着惊艳的嗓音和阳光的性格，还有个关于她的音乐和馈赠世界的大大梦想。她知道，总会有那么一天，只要她一直努力的话，她将让她的爱猫“小包”感到骄傲。"}, {"id": "147002", "num": 2, "name": "K/DA ALL OUT 萨勒芬妮 明日新星", "chromas": false, "image": "//game.gtimg.cn/images/lol/act/img/skinloading/147002.jpg", "hash": "https://cdn.jsdelivr.net/gh/Virace/lol-audio-events-hashtable@main/VO/zh_CN/characters/seraphine/skin2.json", "description": "萨勒芬妮的生活正在超乎她预期地改变着，并且她在尝试着保持她独一无二的嗓音、跟上卡莎剧烈到可怕的编舞、以及设法获得充足的睡眠。"}, {"id": "147003", "num": 3, "name": "K/DA ALL OUT 萨勒芬妮 超级巨星", "chromas": false, "image": "//game.gtimg.cn/images/lol/act/img/skinloading/147003.jpg", "hash": "https://cdn.jsdelivr.net/gh/Virace/lol-audio-events-hashtable@main/VO/zh_CN/characters/seraphine/skin3.json", "description": "在她迅速崛起成为明星后，萨勒芬妮凭借在K/DA新专辑中的表现，已处在世界——还有排行榜——的顶部。她的音乐和她所传达的信息引起了粉丝们的共鸣，并且她很兴奋地向他们展示她在通过音乐发现自我的旅程中发生的事情。"}], "blurb": "萨勒芬妮生在皮城，但父母都是祖安人。她能听到其他人的灵魂——整个世界都在对她唱歌，而她也回以自己的歌声。虽然她小的时候曾被这些声音压得不堪重负，但如今她从这些声音中汲取灵感，将混乱变为协奏。她为这对姊妹城市演唱，提醒这里的人们，他们并不孤单，他们凝聚起来会更强大，在她眼中，他们的潜力是无限的。", "allytips": [], "enemytips": [], "version": "11.12"}