{"id": "TahmKench", "key": "223", "name": "河流之王", "title": "塔姆", "image": "//game.gtimg.cn/images/lol/act/img/champion/TahmKench.png", "skins": [{"id": "223000", "num": 0, "name": "默认皮肤", "chromas": false, "image": "//game.gtimg.cn/images/lol/act/img/skinloading/223000.jpg", "hash": "https://cdn.jsdelivr.net/gh/Virace/lol-audio-events-hashtable@main/VO/zh_CN/characters/tahmkench/skin0.json", "description": null}], "blurb": "塔姆在历史上有许多不同的名字，他游历于符文之地的各条水道，用大意之人的悲惨喂养自己贪得无厌的食欲。虽然他的外表可能富有古怪的魅力和得意，但他在物质领域的漫游只是为了寻找毫无戒心的猎物。他的舌头像巨大的鞭子，即使是全副武装的重甲士兵也会被他从十几步以外的距离击晕，而如果跌入了他隆隆作响的肚子里，就相当于掉进了九死一生的绝命深渊。", "allytips": ["你作为辅助的最重要职能就是确保脆皮友军的安全。时刻留意【大快朵颐】的距离和冷却时间，并且进行相应的走位！", "在使用【厚实表皮】的主动效果时要三思而后行。有的时候，提前获得护盾来规避进一步的伤害是不错的，但有的时候，治疗效果会更加有益。"], "enemytips": ["当你看到塔姆使用了来自【厚实表皮】的护盾时，说明他舍弃了一次可观的治疗。在【厚实表皮】冷却完毕前，他将不会积累新的灰色生命值。", "要留意塔姆的【深渊潜航】 - 你只能用禁锢类控制效果才能打断他的引导。"], "version": "11.14"}